tensnap/__init__.py
tensnap/scenario.py
tensnap/server.py
tensnap/sim_loop.py
tensnap/bindings/__init__.py
tensnap/bindings/basic/__init__.py
tensnap/bindings/basic/accessor.py
tensnap/bindings/basic/action.py
tensnap/bindings/basic/chart.py
tensnap/bindings/basic/parameter.py
tensnap/bindings/mesa/__init__.py
tensnap/bindings/mesa/accessor.py
tensnap/bindings/mesa/datacollector.py
tensnap/bindings/mesa/handler.py
tensnap/examples/cgol.py
tensnap/examples/cgol_viz.py
tensnap/examples/flock.py
tensnap/examples/flock_viz.py
tensnap/examples/hk.py
tensnap/examples/hk_viz.py
tensnap/examples/mushroom.py
tensnap/examples/sirs.py
tensnap/examples/sirs_viz_graph.py
tensnap/examples/sirs_viz_grid.py
tensnap/examples/sugarscape.py
tensnap/examples/sugarscape_viz.py
tensnap/models/__init__.py
tensnap/models/agent.py
tensnap/models/environment.py
tensnap/models/types.py
tensnap/utils/__init__.py
tensnap/utils/attr.py
tensnap/utils/func.py
tensnap/utils/model.py
tensnap/utils/object.py
tensnap/utils/ws.py
tensnap-0.1.0.dist-info/METADATA
tensnap-0.1.0.dist-info/WHEEL
tensnap-0.1.0.dist-info/top_level.txt
tensnap-0.1.0.dist-info/RECORD
