Metadata-Version: 2.4
Name: tensnap
Version: 0.1.0
Summary: Agent-based model visualization toolkit - Python bindings
Author-email: billstark001 <billstark001@example.com>
License: MIT
Project-URL: Homepage, https://github.com/billstark001/tensnap
Project-URL: Documentation, https://github.com/billstark001/tensnap/tree/main/docs
Project-URL: Repository, https://github.com/billstark001/tensnap
Project-URL: Issues, https://github.com/billstark001/tensnap/issues
Keywords: agent-based-modeling,simulation,visualization,abm
Classifier: Development Status :: 3 - Alpha
Classifier: Intended Audience :: Science/Research
Classifier: License :: OSI Approved :: MIT License
Classifier: Programming Language :: Python :: 3
Classifier: Programming Language :: Python :: 3.10
Classifier: Programming Language :: Python :: 3.11
Classifier: Programming Language :: Python :: 3.12
Classifier: Topic :: Scientific/Engineering :: Visualization
Requires-Python: >=3.10
Requires-Dist: numpy>=1.24.0
Requires-Dist: networkx>=3.0
Requires-Dist: msgpack>=1.0.5
Requires-Dist: websockets>=12.0
Requires-Dist: typing-extensions>=4.9.0
Provides-Extra: dev
Requires-Dist: pytest>=7.4.0; extra == "dev"
Requires-Dist: pytest-asyncio>=0.21.0; extra == "dev"
Requires-Dist: pytest-cov>=4.1.0; extra == "dev"
Requires-Dist: mypy>=1.7.0; extra == "dev"
Requires-Dist: ruff>=0.1.0; extra == "dev"
Requires-Dist: black>=23.0.0; extra == "dev"
